noaa_coops/__init__.py
noaa_coops/station.py
noaa_coops-0.3.2.dist-info/LICENSE
noaa_coops-0.3.2.dist-info/WHEEL
noaa_coops-0.3.2.dist-info/METADATA
noaa_coops-0.3.2.dist-info/RECORD
