Metadata-Version: 2.1
Name: noaa-coops
Version: 0.3.2
Summary: Python wrapper for NOAA Tides & Currents Data and Metadata.
Home-page: https://github.com/GClunies/noaa_coops
License: Apache-2.0
Keywords: noaa,coops,tides,currents,weather,api
Author: Greg Clunies
Author-email: greg.clunies@gmail.com
Requires-Python: >=3.8,<4.0
Classifier: License :: OSI Approved :: Apache Software License
Classifier: Programming Language :: Python :: 3
Classifier: Programming Language :: Python :: 3.8
Classifier: Programming Language :: Python :: 3.9
Classifier: Programming Language :: Python :: 3.10
Classifier: Programming Language :: Python :: 3.11
Requires-Dist: pandas (>=1.5.3,<2.0.0)
Requires-Dist: requests (>=2.28.2,<3.0.0)
Requires-Dist: zeep (>=4.2.1,<5.0.0)
Project-URL: Repository, https://github.com/GClunies/noaa_coops
